{"sourcepath":"C:\\NTemplate\\RP_104512_이어드림 화면 프로젝트_scr_1\\edu\\pa\\scr\\cmm\\cm\\scr_guide00.xfdl","items":[{"id":"iknTh6Cark[Static09]","ruleId":"a11y/require-contents-heading","result":"fail","message":"Form Contents에 heading role을 가진 Component가 최소 하나 배치되어야 합니다.[Ln 5, Col 7]","range":{"line":5,"column":7},"tags":["Form","this"]},{"id":"l64hcMWR4n[this]","ruleId":"a11y/match-contents-tab-order","result":"fail","message":"Form Contents의 Component 생성 순서와 taborder의 순서가 맞지 않습니다.[Ln 5, Col 7]","range":{"line":5,"column":7},"tags":["Form","this"]},{"id":"5F1nP7oYAl[Static09]","ruleId":"a11y/require-component-alt-text-props","result":"pass","message":"a11y/require-component-alt-text-props[Ln 6, Col 9]","range":{"line":6,"column":9},"tags":["Static","Static09"]},{"id":"RPSuAiyfis[Static09]","ruleId":"a11y/recommand-component-a11yaction","result":"pass","message":"a11y/recommand-component-a11yaction[Ln 6, Col 9]","range":{"line":6,"column":9},"tags":["Static","Static09"]},{"id":"643fzh07yU[Static09]","ruleId":"a11y-plugin/validate-static-clickevent","result":"pass","message":"a11y-plugin/validate-static-clickevent[Ln 6, Col 9]","range":{"line":6,"column":9},"tags":["Static","Static09"]},{"id":"VyuDlHwDd8[Static09]","ruleId":"a11y-plugin/validate-static-spchar-text","result":"pass","message":"a11y-plugin/validate-static-spchar-text[Ln 6, Col 50]","range":{"line":6,"column":50},"tags":["Static","Static09"]},{"id":"VQ9c4h2fdi[tabMain]","ruleId":"a11y/recommand-component-a11yaction","result":"pass","message":"a11y/recommand-component-a11yaction[Ln 7, Col 9]","range":{"line":7,"column":9},"tags":["Tab","tabMain"]},{"id":"a9aijDkVws[tabMain.Tabpage2]","ruleId":"a11y/require-component-alt-text-props","result":"pass","message":"a11y/require-component-alt-text-props[Ln 10, Col 13]","range":{"line":10,"column":13},"tags":["Tabpage","tabMain.Tabpage2"]},{"id":"u2lGD9AySz[tabMain.Tabpage2]","ruleId":"a11y/recommand-component-a11yaction","result":"pass","message":"a11y/recommand-component-a11yaction[Ln 10, Col 13]","range":{"line":10,"column":13},"tags":["Tabpage","tabMain.Tabpage2"]},{"id":"8JGB943tY2[tabMain.Tabpage3]","ruleId":"a11y/require-component-alt-text-props","result":"pass","message":"a11y/require-component-alt-text-props[Ln 11, Col 13]","range":{"line":11,"column":13},"tags":["Tabpage","tabMain.Tabpage3"]},{"id":"6EUVczpP2G[tabMain.Tabpage3]","ruleId":"a11y/recommand-component-a11yaction","result":"pass","message":"a11y/recommand-component-a11yaction[Ln 11, Col 13]","range":{"line":11,"column":13},"tags":["Tabpage","tabMain.Tabpage3"]},{"id":"r8ND1UjJg1[btn00]","ruleId":"a11y/require-component-alt-text-props","result":"pass","message":"a11y/require-component-alt-text-props[Ln 14, Col 9]","range":{"line":14,"column":9},"tags":["Button","btn00"]},{"id":"gPQIvg1quW[btn00]","ruleId":"a11y/recommand-component-a11yaction","result":"pass","message":"a11y/recommand-component-a11yaction[Ln 14, Col 9]","range":{"line":14,"column":9},"tags":["Button","btn00"]},{"id":"8yr47OTmri[btn00]","ruleId":"a11y-plugin/validate-comp-size","result":"pass","message":"a11y-plugin/validate-comp-size[Ln 14, Col 81]","range":{"line":14,"column":81},"tags":["Button","btn00"]},{"id":"QmLAPWFa9e[Static09]","ruleId":"a11y/require-component-alt-text-props","result":"pass","message":"a11y/require-component-alt-text-props[Ln 18, Col 9]","range":{"line":18,"column":9},"tags":["Static","Static09"]},{"id":"cKLGdjwo83[Static09]","ruleId":"a11y/recommand-component-a11yaction","result":"pass","message":"a11y/recommand-component-a11yaction[Ln 18, Col 9]","range":{"line":18,"column":9},"tags":["Static","Static09"]},{"id":"TReDPZStKe[Static09]","ruleId":"a11y-plugin/validate-static-clickevent","result":"pass","message":"a11y-plugin/validate-static-clickevent[Ln 18, Col 9]","range":{"line":18,"column":9},"tags":["Static","Static09"]},{"id":"a8HLnpFj4g[Static09]","ruleId":"a11y-plugin/validate-static-spchar-text","result":"pass","message":"a11y-plugin/validate-static-spchar-text[Ln 18, Col 9]","range":{"line":18,"column":9},"tags":["Static","Static09"]},{"id":"hwrAbuoThU[tabMain]","ruleId":"a11y/recommand-component-a11yaction","result":"pass","message":"a11y/recommand-component-a11yaction[Ln 19, Col 9]","range":{"line":19,"column":9},"tags":["Tab","tabMain"]}]}