{"sourcepath":"C:\\NTemplate\\RP_104512_이어드림 화면 프로젝트_scr_1\\frame\\par\\frameTopDiv2.xfdl","items":[{"id":"rNhCyiUMvr[sta01]","ruleId":"a11y/require-contents-heading","result":"fail","message":"Form Contents에 heading role을 가진 Component가 최소 하나 배치되어야 합니다.[Ln 5, Col 7]","range":{"line":5,"column":7},"tags":["Form","this"]},{"id":"iEae5t5tlg[this]","ruleId":"a11y/match-contents-tab-order","result":"fail","message":"Form Contents의 Component 생성 순서와 taborder의 순서가 맞지 않습니다.[Ln 5, Col 7]","range":{"line":5,"column":7},"tags":["Form","this"]},{"id":"9JuEXzmusi[sta01]","ruleId":"a11y-plugin/validate-static-clickevent","result":"pass","message":"a11y-plugin/validate-static-clickevent[Ln 6, Col 9]","range":{"line":6,"column":9},"tags":["Static","sta01"]},{"id":"sbo6NSYLdU[sta01]","ruleId":"a11y-plugin/validate-static-spchar-text","result":"pass","message":"a11y-plugin/validate-static-spchar-text[Ln 6, Col 9]","range":{"line":6,"column":9},"tags":["Static","sta01"]},{"id":"ubkpvQh07E[cboStuList]","ruleId":"a11y/require-component-alt-text-props","result":"pass","message":"a11y/require-component-alt-text-props[Ln 7, Col 9]","range":{"line":7,"column":9},"tags":["Combo","cboStuList"]},{"id":"Oe5DG0IIv7[cboStuList]","ruleId":"a11y/recommand-component-a11yaction","result":"fail","message":"accessibilityaction속성은 직관적인 Component동작이 아닌것으로 간주되어, 권장하지 않습니다.[Ln 7, Col 9]","range":{"line":7,"column":9},"tags":["Combo","cboStuList"]},{"id":"WaOZ4k4Scw[sta00]","ruleId":"a11y/require-component-alt-text-props","result":"pass","message":"a11y/require-component-alt-text-props[Ln 8, Col 9]","range":{"line":8,"column":9},"tags":["Static","sta00"]},{"id":"DQTMEZBfdV[sta00]","ruleId":"a11y/recommand-component-a11yaction","result":"pass","message":"a11y/recommand-component-a11yaction[Ln 8, Col 9]","range":{"line":8,"column":9},"tags":["Static","sta00"]},{"id":"1lL0UmEfYC[sta00]","ruleId":"a11y-plugin/validate-static-clickevent","result":"pass","message":"a11y-plugin/validate-static-clickevent[Ln 8, Col 9]","range":{"line":8,"column":9},"tags":["Static","sta00"]},{"id":"zohw4yHsY8[sta00]","ruleId":"a11y-plugin/validate-static-spchar-text","result":"pass","message":"a11y-plugin/validate-static-spchar-text[Ln 8, Col 47]","range":{"line":8,"column":47},"tags":["Static","sta00"]},{"id":"Yb6yOdFPK7[staSchNm]","ruleId":"a11y/require-component-alt-text-props","result":"pass","message":"a11y/require-component-alt-text-props[Ln 9, Col 9]","range":{"line":9,"column":9},"tags":["Static","staSchNm"]},{"id":"Txxl7BCEUY[staSchNm]","ruleId":"a11y/recommand-component-a11yaction","result":"pass","message":"a11y/recommand-component-a11yaction[Ln 9, Col 9]","range":{"line":9,"column":9},"tags":["Static","staSchNm"]},{"id":"0gL5n1iXnl[staSchNm]","ruleId":"a11y-plugin/validate-static-clickevent","result":"pass","message":"a11y-plugin/validate-static-clickevent[Ln 9, Col 9]","range":{"line":9,"column":9},"tags":["Static","staSchNm"]},{"id":"CUMKly3ruA[staSchNm]","ruleId":"a11y-plugin/validate-static-spchar-text","result":"pass","message":"a11y-plugin/validate-static-spchar-text[Ln 9, Col 9]","range":{"line":9,"column":9},"tags":["Static","staSchNm"]},{"id":"aJaQZwuDOK[sta00_01]","ruleId":"a11y/require-component-alt-text-props","result":"pass","message":"a11y/require-component-alt-text-props[Ln 10, Col 9]","range":{"line":10,"column":9},"tags":["Static","sta00_01"]},{"id":"vgn9aXZI1d[sta00_01]","ruleId":"a11y/recommand-component-a11yaction","result":"pass","message":"a11y/recommand-component-a11yaction[Ln 10, Col 9]","range":{"line":10,"column":9},"tags":["Static","sta00_01"]},{"id":"38IMI1EYoR[sta00_01]","ruleId":"a11y-plugin/validate-static-clickevent","result":"pass","message":"a11y-plugin/validate-static-clickevent[Ln 10, Col 9]","range":{"line":10,"column":9},"tags":["Static","sta00_01"]},{"id":"iA7Nby2CxX[sta00_01]","ruleId":"a11y-plugin/validate-static-spchar-text","result":"pass","message":"a11y-plugin/validate-static-spchar-text[Ln 10, Col 50]","range":{"line":10,"column":50},"tags":["Static","sta00_01"]},{"id":"jnAm0bpX87[cboStuList]","ruleId":"a11y/require-component-alt-text-props","result":"pass","message":"a11y/require-component-alt-text-props[Ln 13, Col 9]","range":{"line":13,"column":9},"tags":["Combo","cboStuList"]},{"id":"wLpSod3K4j[cboStuList]","ruleId":"a11y/recommand-component-a11yaction","result":"fail","message":"accessibilityaction속성은 직관적인 Component동작이 아닌것으로 간주되어, 권장하지 않습니다.[Ln 13, Col 9]","range":{"line":13,"column":9},"tags":["Combo","cboStuList"]},{"id":"wzhqJpwTC4[sta00]","ruleId":"a11y/require-component-alt-text-props","result":"pass","message":"a11y/require-component-alt-text-props[Ln 14, Col 9]","range":{"line":14,"column":9},"tags":["Static","sta00"]},{"id":"SPsPlgWwPa[sta00]","ruleId":"a11y/recommand-component-a11yaction","result":"pass","message":"a11y/recommand-component-a11yaction[Ln 14, Col 9]","range":{"line":14,"column":9},"tags":["Static","sta00"]},{"id":"AV9xRTTJuZ[sta00]","ruleId":"a11y-plugin/validate-static-clickevent","result":"pass","message":"a11y-plugin/validate-static-clickevent[Ln 14, Col 9]","range":{"line":14,"column":9},"tags":["Static","sta00"]},{"id":"wUYLDF6gFH[sta00]","ruleId":"a11y-plugin/validate-static-spchar-text","result":"pass","message":"a11y-plugin/validate-static-spchar-text[Ln 14, Col 251]","range":{"line":14,"column":251},"tags":["Static","sta00"]},{"id":"c6bnMvmxka[sta01]","ruleId":"a11y-plugin/validate-static-clickevent","result":"pass","message":"a11y-plugin/validate-static-clickevent[Ln 15, Col 9]","range":{"line":15,"column":9},"tags":["Static","sta01"]},{"id":"7Jho6V1PNM[sta01]","ruleId":"a11y-plugin/validate-static-spchar-text","result":"pass","message":"a11y-plugin/validate-static-spchar-text[Ln 15, Col 9]","range":{"line":15,"column":9},"tags":["Static","sta01"]},{"id":"zektQbMyFn[sta00_01]","ruleId":"a11y/require-component-alt-text-props","result":"pass","message":"a11y/require-component-alt-text-props[Ln 17, Col 9]","range":{"line":17,"column":9},"tags":["Static","sta00_01"]},{"id":"uNIf6PGbcv[sta00_01]","ruleId":"a11y/recommand-component-a11yaction","result":"pass","message":"a11y/recommand-component-a11yaction[Ln 17, Col 9]","range":{"line":17,"column":9},"tags":["Static","sta00_01"]},{"id":"zsFhd45A9q[sta00_01]","ruleId":"a11y-plugin/validate-static-clickevent","result":"pass","message":"a11y-plugin/validate-static-clickevent[Ln 17, Col 9]","range":{"line":17,"column":9},"tags":["Static","sta00_01"]},{"id":"NC943YTW1U[sta00_01]","ruleId":"a11y-plugin/validate-static-spchar-text","result":"pass","message":"a11y-plugin/validate-static-spchar-text[Ln 17, Col 9]","range":{"line":17,"column":9},"tags":["Static","sta00_01"]}]}