{"sourcepath":"C:\\NTemplate\\RP_104512_이어드림 화면 프로젝트_scr_1\\template\\Survey04-frametop.xfdl","items":[{"id":"SDk9aWOkhG[this]","ruleId":"a11y/match-contents-tab-order","result":"fail","message":"Form Contents의 Component 생성 순서와 taborder의 순서가 맞지 않습니다.[Ln 5, Col 7]","range":{"line":5,"column":7},"tags":["Form","this"]},{"id":"PiEPIWCyWV[Div]","ruleId":"a11y/match-contents-tab-order","result":"pass","message":"a11y/match-contents-tab-order[Ln 0, Col 0]","range":{"line":0,"column":0},"tags":["Div","Div"]},{"id":"pPJNk59Vti[div00.form.sta01]","ruleId":"a11y-plugin/validate-static-clickevent","result":"pass","message":"a11y-plugin/validate-static-clickevent[Ln 9, Col 15]","range":{"line":9,"column":15},"tags":["Static","div00.form.sta01"]},{"id":"eWXNVSeLr6[div00.form.sta01]","ruleId":"a11y-plugin/validate-static-spchar-text","result":"pass","message":"a11y-plugin/validate-static-spchar-text[Ln 9, Col 15]","range":{"line":9,"column":15},"tags":["Static","div00.form.sta01"]},{"id":"g8phCVzmZz[div00.form.sta00]","ruleId":"a11y/require-component-alt-text-props","result":"pass","message":"a11y/require-component-alt-text-props[Ln 10, Col 15]","range":{"line":10,"column":15},"tags":["Static","div00.form.sta00"]},{"id":"7sRQgjGAd3[div00.form.sta00]","ruleId":"a11y/recommand-component-a11yaction","result":"pass","message":"a11y/recommand-component-a11yaction[Ln 10, Col 15]","range":{"line":10,"column":15},"tags":["Static","div00.form.sta00"]},{"id":"G4W92wLqDF[div00.form.sta00]","ruleId":"a11y-plugin/validate-static-clickevent","result":"pass","message":"a11y-plugin/validate-static-clickevent[Ln 10, Col 15]","range":{"line":10,"column":15},"tags":["Static","div00.form.sta00"]},{"id":"GmZj5NCA2f[div00.form.sta00]","ruleId":"a11y-plugin/validate-static-spchar-text","result":"pass","message":"a11y-plugin/validate-static-spchar-text[Ln 10, Col 53]","range":{"line":10,"column":53},"tags":["Static","div00.form.sta00"]},{"id":"vGgAgPHEKK[div00.form.sta00_00]","ruleId":"a11y/require-component-alt-text-props","result":"pass","message":"a11y/require-component-alt-text-props[Ln 11, Col 15]","range":{"line":11,"column":15},"tags":["Static","div00.form.sta00_00"]},{"id":"N5GI8AsYIZ[div00.form.sta00_00]","ruleId":"a11y/recommand-component-a11yaction","result":"pass","message":"a11y/recommand-component-a11yaction[Ln 11, Col 15]","range":{"line":11,"column":15},"tags":["Static","div00.form.sta00_00"]},{"id":"4k3oIyPgy1[div00.form.sta00_00]","ruleId":"a11y-plugin/validate-static-clickevent","result":"pass","message":"a11y-plugin/validate-static-clickevent[Ln 11, Col 15]","range":{"line":11,"column":15},"tags":["Static","div00.form.sta00_00"]},{"id":"GOU2JNRzDV[div00.form.sta00_00]","ruleId":"a11y-plugin/validate-static-spchar-text","result":"pass","message":"a11y-plugin/validate-static-spchar-text[Ln 11, Col 56]","range":{"line":11,"column":56},"tags":["Static","div00.form.sta00_00"]},{"id":"5m4qgtqIFl[div00.form.sta00_00_00]","ruleId":"a11y/require-component-alt-text-props","result":"pass","message":"a11y/require-component-alt-text-props[Ln 12, Col 15]","range":{"line":12,"column":15},"tags":["Static","div00.form.sta00_00_00"]},{"id":"5BagF5Vfdu[div00.form.sta00_00_00]","ruleId":"a11y/recommand-component-a11yaction","result":"pass","message":"a11y/recommand-component-a11yaction[Ln 12, Col 15]","range":{"line":12,"column":15},"tags":["Static","div00.form.sta00_00_00"]},{"id":"pcvEtPFOJy[div00.form.sta00_00_00]","ruleId":"a11y-plugin/validate-static-clickevent","result":"pass","message":"a11y-plugin/validate-static-clickevent[Ln 12, Col 15]","range":{"line":12,"column":15},"tags":["Static","div00.form.sta00_00_00"]},{"id":"8W28lKgOaQ[div00.form.sta00_00_00]","ruleId":"a11y-plugin/validate-static-spchar-text","result":"pass","message":"a11y-plugin/validate-static-spchar-text[Ln 12, Col 59]","range":{"line":12,"column":59},"tags":["Static","div00.form.sta00_00_00"]},{"id":"3LTdUoOS99[div00.form.btn00]","ruleId":"a11y/require-component-alt-text-props","result":"pass","message":"a11y/require-component-alt-text-props[Ln 13, Col 15]","range":{"line":13,"column":15},"tags":["Button","div00.form.btn00"]},{"id":"ptcowcnF2g[div00.form.btn00]","ruleId":"a11y/recommand-component-a11yaction","result":"pass","message":"a11y/recommand-component-a11yaction[Ln 13, Col 15]","range":{"line":13,"column":15},"tags":["Button","div00.form.btn00"]},{"id":"3kHs4uZCDK[div00.form.btn00]","ruleId":"a11y-plugin/validate-comp-size","result":"pass","message":"a11y-plugin/validate-comp-size[Ln 13, Col 86]","range":{"line":13,"column":86},"tags":["Button","div00.form.btn00"]},{"id":"YPrBp4vUGV[div00.form.sta02]","ruleId":"a11y-plugin/validate-static-clickevent","result":"pass","message":"a11y-plugin/validate-static-clickevent[Ln 14, Col 15]","range":{"line":14,"column":15},"tags":["Static","div00.form.sta02"]},{"id":"z98fQODoqn[div00.form.sta02]","ruleId":"a11y-plugin/validate-static-spchar-text","result":"pass","message":"a11y-plugin/validate-static-spchar-text[Ln 14, Col 15]","range":{"line":14,"column":15},"tags":["Static","div00.form.sta02"]},{"id":"y0uiAbu7WF[div00.form.btn00_00]","ruleId":"a11y/require-component-alt-text-props","result":"pass","message":"a11y/require-component-alt-text-props[Ln 15, Col 15]","range":{"line":15,"column":15},"tags":["Button","div00.form.btn00_00"]},{"id":"8LndkQVHMt[div00.form.btn00_00]","ruleId":"a11y/recommand-component-a11yaction","result":"pass","message":"a11y/recommand-component-a11yaction[Ln 15, Col 15]","range":{"line":15,"column":15},"tags":["Button","div00.form.btn00_00"]},{"id":"DwWmGl0kwz[div00.form.btn00_00]","ruleId":"a11y-plugin/validate-comp-size","result":"pass","message":"a11y-plugin/validate-comp-size[Ln 15, Col 91]","range":{"line":15,"column":91},"tags":["Button","div00.form.btn00_00"]},{"id":"ngX69tMxyT[div00.form.sta00]","ruleId":"a11y/require-component-alt-text-props","result":"pass","message":"a11y/require-component-alt-text-props[Ln 19, Col 15]","range":{"line":19,"column":15},"tags":["Static","div00.form.sta00"]},{"id":"XyLHFUisI8[div00.form.sta00]","ruleId":"a11y/recommand-component-a11yaction","result":"pass","message":"a11y/recommand-component-a11yaction[Ln 19, Col 15]","range":{"line":19,"column":15},"tags":["Static","div00.form.sta00"]},{"id":"w5td7qDlpa[div00.form.sta00]","ruleId":"a11y-plugin/validate-static-clickevent","result":"pass","message":"a11y-plugin/validate-static-clickevent[Ln 19, Col 15]","range":{"line":19,"column":15},"tags":["Static","div00.form.sta00"]},{"id":"HgVa35tmoV[div00.form.sta00]","ruleId":"a11y-plugin/validate-static-spchar-text","result":"pass","message":"a11y-plugin/validate-static-spchar-text[Ln 19, Col 160]","range":{"line":19,"column":160},"tags":["Static","div00.form.sta00"]},{"id":"61eZuUgXJ2[div00.form.sta00_00]","ruleId":"a11y/require-component-alt-text-props","result":"pass","message":"a11y/require-component-alt-text-props[Ln 21, Col 15]","range":{"line":21,"column":15},"tags":["Static","div00.form.sta00_00"]},{"id":"UKiweGiQwE[div00.form.sta00_00]","ruleId":"a11y/recommand-component-a11yaction","result":"pass","message":"a11y/recommand-component-a11yaction[Ln 21, Col 15]","range":{"line":21,"column":15},"tags":["Static","div00.form.sta00_00"]},{"id":"fozptY4AdR[div00.form.sta00_00]","ruleId":"a11y-plugin/validate-static-clickevent","result":"pass","message":"a11y-plugin/validate-static-clickevent[Ln 21, Col 15]","range":{"line":21,"column":15},"tags":["Static","div00.form.sta00_00"]},{"id":"7GEUO0IWSV[div00.form.sta00_00]","ruleId":"a11y-plugin/validate-static-spchar-text","result":"pass","message":"a11y-plugin/validate-static-spchar-text[Ln 21, Col 132]","range":{"line":21,"column":132},"tags":["Static","div00.form.sta00_00"]},{"id":"f5K2K23NMf[div00.form.btn00]","ruleId":"a11y/require-component-alt-text-props","result":"pass","message":"a11y/require-component-alt-text-props[Ln 22, Col 15]","range":{"line":22,"column":15},"tags":["Button","div00.form.btn00"]},{"id":"bjurmfha9z[div00.form.btn00]","ruleId":"a11y/recommand-component-a11yaction","result":"pass","message":"a11y/recommand-component-a11yaction[Ln 22, Col 15]","range":{"line":22,"column":15},"tags":["Button","div00.form.btn00"]},{"id":"yr64XUrhCV[div00.form.sta00]","ruleId":"a11y/require-component-alt-text-props","result":"pass","message":"a11y/require-component-alt-text-props[Ln 29, Col 15]","range":{"line":29,"column":15},"tags":["Static","div00.form.sta00"]},{"id":"ARG4IYf8DE[div00.form.sta00]","ruleId":"a11y/recommand-component-a11yaction","result":"pass","message":"a11y/recommand-component-a11yaction[Ln 29, Col 15]","range":{"line":29,"column":15},"tags":["Static","div00.form.sta00"]},{"id":"6BA9h25ImI[div00.form.sta00]","ruleId":"a11y-plugin/validate-static-clickevent","result":"pass","message":"a11y-plugin/validate-static-clickevent[Ln 29, Col 15]","range":{"line":29,"column":15},"tags":["Static","div00.form.sta00"]},{"id":"hszm8z2VDS[div00.form.sta00]","ruleId":"a11y-plugin/validate-static-spchar-text","result":"pass","message":"a11y-plugin/validate-static-spchar-text[Ln 29, Col 173]","range":{"line":29,"column":173},"tags":["Static","div00.form.sta00"]},{"id":"HRwnisUWBn[div00.form.sta00_00]","ruleId":"a11y/require-component-alt-text-props","result":"pass","message":"a11y/require-component-alt-text-props[Ln 31, Col 15]","range":{"line":31,"column":15},"tags":["Static","div00.form.sta00_00"]},{"id":"dwThiIapN9[div00.form.sta00_00]","ruleId":"a11y/recommand-component-a11yaction","result":"pass","message":"a11y/recommand-component-a11yaction[Ln 31, Col 15]","range":{"line":31,"column":15},"tags":["Static","div00.form.sta00_00"]},{"id":"gcZZMZK8DT[div00.form.sta00_00]","ruleId":"a11y-plugin/validate-static-clickevent","result":"pass","message":"a11y-plugin/validate-static-clickevent[Ln 31, Col 15]","range":{"line":31,"column":15},"tags":["Static","div00.form.sta00_00"]},{"id":"03SDfTMvqO[div00.form.sta00_00]","ruleId":"a11y-plugin/validate-static-spchar-text","result":"pass","message":"a11y-plugin/validate-static-spchar-text[Ln 31, Col 132]","range":{"line":31,"column":132},"tags":["Static","div00.form.sta00_00"]},{"id":"kGtrQLRbXG[div00.form.btn00]","ruleId":"a11y/require-component-alt-text-props","result":"pass","message":"a11y/require-component-alt-text-props[Ln 32, Col 15]","range":{"line":32,"column":15},"tags":["Button","div00.form.btn00"]},{"id":"PsRyln8T8C[div00.form.btn00]","ruleId":"a11y/recommand-component-a11yaction","result":"pass","message":"a11y/recommand-component-a11yaction[Ln 32, Col 15]","range":{"line":32,"column":15},"tags":["Button","div00.form.btn00"]}]}